[
    {
        "icon": "https://i.ibb.co/W3zj4GZ/activity.png",
        "title": "Grow Your Business",
        "des": "We help identify the best ways to improve your business",
        "url": "#"
    },
    {
        "icon": "https://i.ibb.co/47dywZF/heart.png",
        "title": "Improve brand loyalty",
        "des": "We help identify the best ways to improve your business",
        "url": "#"
    },
    {
        "icon": "https://i.ibb.co/Mgj0fBD/work.png",
        "title": "Improve Business Model",
        "des": "We help identify the best ways to improve your business",
        "url": "#"
    }

]